swaggertools/__init__.py
swaggertools/__main__.py
swaggertools/_version.py
swaggertools/bases.py
swaggertools/cli.py
swaggertools/loaders.py
swaggertools/spec.py
swaggertools/util.py
swaggertools/yaml.py
swaggertools-0.0.4.dist-info/DESCRIPTION.rst
swaggertools-0.0.4.dist-info/METADATA
swaggertools-0.0.4.dist-info/RECORD
swaggertools-0.0.4.dist-info/WHEEL
swaggertools-0.0.4.dist-info/entry_points.txt
swaggertools-0.0.4.dist-info/metadata.json
swaggertools-0.0.4.dist-info/top_level.txt
