Metadata-Version: 2.0
Name: swaggertools
Version: 0.0.4
Summary: Merge many files swagger specification into one file.
Home-page: http://swagger.errorist.io/tools
Author: Xavier Barbosa
Author-email: clint.northwood@gmail.com
License: MIT
Keywords: api,json,yaml,utilitaries,validation,swagger
Platform: UNKNOWN
Classifier: Development Status :: 4 - Beta
Classifier: Environment :: Console
Classifier: Environment :: OpenStack
Classifier: Intended Audience :: Developers
Classifier: Intended Audience :: Information Technology
Classifier: License :: OSI Approved :: Apache Software License
Classifier: Operating System :: OS Independent
Classifier: Programming Language :: Python
Classifier: Programming Language :: Python :: 3
Classifier: Programming Language :: Python :: 3.4
Classifier: Programming Language :: Python :: 3.5
Requires-Dist: dominate
Requires-Dist: pyyaml
